.gitignore
.travis.yml
CHANGELOG.rst
CONTRIBUTORS
LICENSE
MANIFEST.in
README.rst
discurses.py
example_discurses.yaml
setup.py
docs/graphics/img-2016-10-06-142806.png
requirements/base.in
requirements/base.txt
requirements/dev.in
requirements/dev.txt
src/discurses/__about__.py
src/discurses/__init__.py
src/discurses/__main__.py
src/discurses/config.py
src/discurses/discord.py
src/discurses/keybinds.py
src/discurses/keymaps.py
src/discurses/log.py
src/discurses/processing.py
src/discurses.egg-info/PKG-INFO
src/discurses.egg-info/SOURCES.txt
src/discurses.egg-info/dependency_links.txt
src/discurses.egg-info/entry_points.txt
src/discurses.egg-info/not-zip-safe
src/discurses.egg-info/requires.txt
src/discurses.egg-info/top_level.txt
src/discurses/ui/__init__.py
src/discurses/ui/chat.py
src/discurses/ui/has_modal.py
src/discurses/ui/main.py
src/discurses/ui/member_list.py
src/discurses/ui/message_list.py
src/discurses/ui/message_textbox.py
src/discurses/ui/server_tree.py
src/discurses/ui/statusbar.py
src/discurses/ui/lib/__init__.py
src/discurses/ui/lib/text_edit.py