Metadata-Version: 1.2
Name: discurses
Version: 0.3.5
Summary: Discord CLI client written in Python, based on urwid.
Home-page: https://github.com/topisani/discurses
Author: Topisani
Author-email: topisani@hamsterpoison.com
License: https://github.com/topisani/discurses
Platform: UNKNOWN
Requires-Python: >=3.6, !=3.7.*
